Metadata-Version: 2.1
Name: PragyanAPI
Version: 0.6.5.6
Summary: python api hub | PragyanAPI
Home-page: https://github.com/pragyancoder/PragyanAPI
Download-URL: https://github.com/pragyancoder/PragyanAPI/blob/main/README.md
Author: CoderPragyan | CoderPragyan
Author-email: coderpragyan@gmail.com
License: MIT
Project-URL: Tracker, https://github.com/PRAGYANCODER/PragyanAPI/issues
Project-URL: Community, https://t.me/pragyancoder
Project-URL: Source, https://github.com/pragyancoder/PragyanAPI
Keywords: python,PragyanAPI,flask
Classifier: Development Status :: 5 - Production/Stable
Classifier: Intended Audience :: Developers
Classifier: Natural Language :: English
Classifier: Operating System :: OS Independent
Classifier: Programming Language :: Python
Classifier: Programming Language :: Python :: 3
Classifier: Programming Language :: Python :: 3.7
Classifier: Programming Language :: Python :: 3.8
Classifier: Programming Language :: Python :: 3.9
Classifier: Programming Language :: Python :: 3.10
Classifier: Programming Language :: Python :: 3.11
Classifier: Programming Language :: Python :: 3.12
Classifier: Programming Language :: Python :: Implementation
Classifier: Programming Language :: Python :: Implementation :: CPython
Classifier: Programming Language :: Python :: Implementation :: PyPy
Classifier: Topic :: Internet
Classifier: Topic :: Communications
Classifier: Topic :: Communications :: Chat
Classifier: Topic :: Software Development :: Libraries
Classifier: Topic :: Software Development :: Libraries :: Python Modules
Classifier: Topic :: Software Development :: Libraries :: Application Frameworks
Requires-Python: ~=3.7
License-File: LICENSE
Requires-Dist: pytz>=2023.3
Requires-Dist: requests-html
Requires-Dist: pillow
Requires-Dist: lxml_html_clean
